cruft/__init__.py
cruft/__main__.py
cruft/_cli.py
cruft/_logo.py
cruft/_version.py
cruft/exceptions.py
cruft/py.typed
cruft/_commands/__init__.py
cruft/_commands/check.py
cruft/_commands/create.py
cruft/_commands/diff.py
cruft/_commands/link.py
cruft/_commands/update.py
cruft/_commands/utils/__init__.py
cruft/_commands/utils/cookiecutter.py
cruft/_commands/utils/cruft.py
cruft/_commands/utils/diff.py
cruft/_commands/utils/generate.py
cruft/_commands/utils/iohelper.py
cruft-2.16.0.dist-info/METADATA
cruft-2.16.0.dist-info/WHEEL
cruft-2.16.0.dist-info/entry_points.txt
cruft-2.16.0.dist-info/licenses/LICENSE
cruft-2.16.0.dist-info/RECORD
