Metadata-Version: 2.4
Name: cruft
Version: 2.16.0
Summary: Allows you to maintain all the necessary cruft for packaging and building projects separate from the code you intentionally write. Built on-top of CookieCutter.
Author-email: Timothy Crosley <timothy.crosley@gmail.com>, Sambhav Kothari <sambhavs.email@gmail.com>
License: MIT
License-File: LICENSE
Requires-Python: >=3.7
Requires-Dist: click>=7.1.2
Requires-Dist: cookiecutter>=1.7
Requires-Dist: gitpython>=3.0
Requires-Dist: importlib-metadata<5.0.0,>=2.0.0; python_version < '3.8'
Requires-Dist: toml>=0.10; python_version < '3.11'
Requires-Dist: typer>=0.4.0
Provides-Extra: pyproject
Requires-Dist: toml; extra == 'pyproject'
